gearmind_sdk/__init__.py
gearmind_sdk/_version.py
gearmind_sdk/gearmind_sdk.py
gearmind_sdk-0.0.post1.dist-info/LICENSE
gearmind_sdk-0.0.post1.dist-info/METADATA
gearmind_sdk-0.0.post1.dist-info/WHEEL
gearmind_sdk-0.0.post1.dist-info/top_level.txt
gearmind_sdk-0.0.post1.dist-info/RECORD
