Metadata-Version: 2.1
Name: gearmind-sdk
Version: 0.0.post1
Summary: A Python SDK for interacting with the GearMind API
Author-email: Patcharaphon Srida <muc5674@gmail.com>
License: MIT
Project-URL: Homepage, https://github.com/mengsokool/gearmind-sdk-python
Project-URL: Bug Tracker, https://github.com/mengsokool/gearmind-sdk-python/issues
Keywords: gearmind,api,sdk
Classifier: Programming Language :: Python :: 3
Classifier: License :: OSI Approved :: MIT License
Classifier: Operating System :: OS Independent
Requires-Python: >=3.7
License-File: LICENSE
Requires-Dist: requests>=2.25.0
